fastlbp/__init__.py
fastlbp/_lbp.cpython-312-x86_64-linux-gnu.so
fastlbp/_lbp_gpu.cpython-312-x86_64-linux-gnu.so
fastlbp/common.py
fastlbp/fastlbp.py
fastlbp/lbp.py
fastlbp/utils.py
fastlbp/workers.py
fastlbp/cuda/_lbp_gpu.cpp
fastlbp/cuda/_lbp_gpu.pyx
fastlbp/cuda/test.py
fastlbp/cuda/cuda/common.h
fastlbp/cuda/cuda/main.cu
fastlbp/cuda/cuda/main.h
fastlbp.libs/libcudart-96c42e41.so.13.0.96
fastlbp-0.3.3.dist-info/METADATA
fastlbp-0.3.3.dist-info/WHEEL
fastlbp-0.3.3.dist-info/top_level.txt
fastlbp-0.3.3.dist-info/RECORD
fastlbp-0.3.3.dist-info/licenses/LICENSE
fastlbp-0.3.3.dist-info/sboms/auditwheel.cdx.json
